spi_sub.v
module spi_sub (
    input reset,
    input [7:0] data_in,
    input load,
    output reg [7:0] data_out,
    output reg ready,
    output reg done,
    input mosi,
    output reg miso,
    input sclk,
    input cs
);

// Registradores para controle interno
reg [7:0] shift_reg_in; // Registro de deslocamento para entrada
reg [7:0] shift_reg_out; // Registro de deslocamento para saída
reg [2:0] bit_count = 0; // Contador de bits
reg load_reg = 0; // Indica que o dado foi carregado

// Processamento na borda de descida do sclk e controle por cs
always @(negedge sclk or posedge reset) begin
    if (reset) begin
        // Reseta o estado do módulo
        shift_reg_in <= 0;
        shift_reg_out <= 0;
        data_out <= 0;
        ready <= 0;
        done <= 0;
        miso <= 1'b0;
        bit_count <= 0;
        load_reg <= 0;
    end else if (!cs) begin
        // cs ativo
        if (load && !load_reg) begin
            // Carrega o dado para transmissão
            shift_reg_out <= data_in;
            load_reg <= 1;
            done <= 1; // Indica que o dado de entrada foi lido
        end else if (load_reg) begin
            // Transmite e recebe dados
            if (bit_count < 8) begin
                miso <= shift_reg_out[7]; // Envia o bit mais significativo
                shift_reg_out <= shift_reg_out << 1; // Desloca para preparar o próximo bit
                shift_reg_in <= (shift_reg_in << 1) | mosi; // Recebe o próximo bit
                bit_count <= bit_count + 1;
            end
            if (bit_count == 7) begin
                // Transmissão/recepção completa
                ready <= 1; // Dados recebidos disponíveis
                data_out <= shift_reg_in; // Transfere os dados recebidos
                bit_count <= 0; // Reseta o contador para a próxima operação
                load_reg <= 0; // Reseta o indicador de carga
            end
        end
    end else if (cs) begin
        // cs inativo, prepara para a próxima transmissão
        done <= 0;
        ready <= 0;
    end
end

endmodule

spi_main.v
module spi_main (
    input clk,
    input reset,
    input [7:0] data_in,
    input load,
    output reg [7:0] data_out,
    output reg ready,
    output reg done,
    output reg mosi,
    input miso,
    output reg sclk,
    output reg cs
);

// Registradores internos
reg [7:0] shift_reg;
reg [2:0] bit_counter; // Contador para os bits a serem transmitidos
reg load_reg;

// Controle do clock SPI (sclk) - gerar em metade da frequência do clk principal
reg clk_divider;
always @(posedge clk) begin
    if (reset) clk_divider <= 0;
    else clk_divider <= ~clk_divider;

    sclk = clk_divider;
end


// Lógica principal
always @(posedge clk) begin
    if (reset) begin
        cs <= 1;
        done <= 0;
        ready <= 0;
        bit_counter <= 0;
        load_reg <= 0;
    end else if (load && !load_reg) begin
        shift_reg <= data_in;
        cs <= 0; // Iniciar transmissão
        bit_counter <= 7;
        load_reg <= 1;
    end else if (load_reg) begin
        if (clk_divider) begin // Na borda de subida de sclk
            mosi <= shift_reg[7];
            shift_reg <= shift_reg << 1;
            if (bit_counter > 0) bit_counter <= bit_counter - 1;
            else begin
                cs <= 1; // Finalizar transmissão
                done <= 1;
                load_reg <= 0;
            end
        end else begin
            done <= 0; // Resetar sinal de 'done' na borda de descida
        end
    end
end

endmodule

tb_spi.v
module tb_spi();

// Sinais gerais
reg clk;
reg reset;

// Sinais para o Principal (Main)
reg [7:0] mdata_in;
wire [7:0] mdata_out;
reg mload;
wire mready, mdone; 

// Sinais de comunicação entre os módulos
wire mosi, miso, sclk, cs;

// Sinais do Secundário (Sub)
reg [7:0] sdata_in;
wire [7:0] sdata_out;
reg sload;
wire sready, sdone;

spi_main spm(
    .clk(clk),
    .reset(reset),
    .data_in(mdata_in),
    .load(mload),
    .data_out(mdata_out),
    .ready(mready),
    .done(mdone),
    .mosi(mosi),
    .miso(miso),
    .sclk(sclk),
    .cs(cs)
);

spi_sub sps(
    .reset(reset),
    .data_in(sdata_in),
    .load(sload),
    .data_out(sdata_out),
    .ready(sready),
    .done(sdone),
    .mosi(mosi),
    .miso(miso),
    .sclk(sclk),
    .cs(cs)
);

always #1 clk = (clk===1'b0);

initial begin
  $dumpfile("tb_spi.vcd");
  $dumpvars(0, tb_spi);

  reset = 1;
  mload = 0; mdata_in = 0; 
  sload = 0; sdata_in = 0;

  #10 reset = 0;
  #1;
  mload = 1; mdata_in = 8'b10101010;
  #2 mload = 0;

  #20;

  mload = 1; mdata_in = 8'b11001100;
  #2 mload = 0;

  #20;

  sload = 1; sdata_in = 8'b11110000;
  #2 sload = 0;

  #20;

  sload = 1; sdata_in = 8'b00001111;
  #2 sload = 0;

  #20;

  $finish;
end

// Só imprime os sinais de saída quando um dos dois ready é 1
initial begin
  forever begin
    if (mready) begin
      $display("mready=%b, mdata_out=%b", mready, mdata_out);
    end
    if (sready) begin
      $display("sready=%b, sdata_out=%b", sready, sdata_out);
    end
    #2;
  end
end

endmodule

tb_spi.vcd
$date
	Mon Mar 18 10:33:54 2024
$end
$version
	Icarus Verilog
$end
$timescale
	1s
$end
$scope module tb_spi $end
$var wire 1 ! sready $end
$var wire 1 " sdone $end
$var wire 8 # sdata_out [7:0] $end
$var wire 1 $ sclk $end
$var wire 1 % mready $end
$var wire 1 & mosi $end
$var wire 1 ' miso $end
$var wire 1 ( mdone $end
$var wire 8 ) mdata_out [7:0] $end
$var wire 1 * cs $end
$var reg 1 + clk $end
$var reg 8 , mdata_in [7:0] $end
$var reg 1 - mload $end
$var reg 1 . reset $end
$var reg 8 / sdata_in [7:0] $end
$var reg 1 0 sload $end
$scope module spm $end
$var wire 1 + clk $end
$var wire 8 1 data_in [7:0] $end
$var wire 1 - load $end
$var wire 1 . reset $end
$var wire 1 ' miso $end
$var reg 3 2 bit_counter [2:0] $end
$var reg 1 3 clk_divider $end
$var reg 1 * cs $end
$var reg 8 4 data_out [7:0] $end
$var reg 1 ( done $end
$var reg 1 5 load_reg $end
$var reg 1 & mosi $end
$var reg 1 % ready $end
$var reg 1 $ sclk $end
$var reg 8 6 shift_reg [7:0] $end
$upscope $end
$scope module sps $end
$var wire 1 * cs $end
$var wire 8 7 data_in [7:0] $end
$var wire 1 0 load $end
$var wire 1 & mosi $end
$var wire 1 . reset $end
$var wire 1 $ sclk $end
$var reg 3 8 bit_count [2:0] $end
$var reg 8 9 data_out [7:0] $end
$var reg 1 " done $end
$var reg 1 : load_reg $end
$var reg 1 ' miso $end
$var reg 1 ! ready $end
$var reg 8 ; shift_reg_in [7:0] $end
$var reg 8 < shift_reg_out [7:0] $end
$upscope $end
$upscope $end
$enddefinitions $end
#0
$dumpvars
b0 <
b0 ;
0:
b0 9
b0 8
b0 7
bx 6
x5
bx 4
x3
bx 2
b0 1
00
b0 /
1.
0-
b0 ,
x+
x*
bx )
x(
0'
x&
x%
x$
b0 #
0"
0!
$end
#1
0+
#2
03
05
b0 2
0%
0(
1*
1+
#3
0+
#4
0$
1+
#5
0+
#6
1+
#7
0+
#8
1+
#9
0+
#10
13
1+
0.
#11
0+
b10101010 ,
b10101010 1
1-
#12
15
b111 2
0*
b10101010 6
03
1$
1+
#13
0+
0-
#14
13
0$
1+
#15
0+
#16
b110 2
b1010100 6
1&
03
1$
1+
#17
0+
#18
13
0$
1+
#19
0+
#20
b101 2
b10101000 6
0&
03
1$
1+
#21
0+
#22
13
0$
1+
#23
0+
#24
b100 2
b1010000 6
1&
03
1$
1+
#25
0+
#26
13
0$
1+
#27
0+
#28
b11 2
b10100000 6
0&
03
1$
1+
#29
0+
#30
13
0$
1+
#31
0+
#32
b10 2
b1000000 6
1&
03
1$
1+
#33
0+
b11001100 ,
b11001100 1
1-
#34
13
0$
1+
#35
0+
0-
#36
b1 2
b10000000 6
0&
03
1$
1+
#37
0+
#38
13
0$
1+
#39
0+
#40
b0 2
b0 6
1&
03
1$
1+
#41
0+
#42
13
0$
1+
#43
0+
#44
05
1(
1*
0&
03
1$
1+
#45
0+
#46
13
0$
1+
#47
0+
#48
03
1$
1+
#49
0+
#50
13
0$
1+
#51
0+
#52
03
1$
1+
#53
0+
#54
13
0$
1+
#55
0+
b11110000 /
b11110000 7
10
#56
03
1$
1+
#57
0+
00
#58
13
0$
1+
#59
0+
#60
03
1$
1+
#61
0+
#62
13
0$
1+
#63
0+
#64
03
1$
1+
#65
0+
#66
13
0$
1+
#67
0+
#68
03
1$
1+
#69
0+
#70
13
0$
1+
#71
0+
#72
03
1$
1+
#73
0+
#74
13
0$
1+
#75
0+
#76
03
1$
1+
#77
0+
b1111 /
b1111 7
10
#78
13
0$
1+
#79
0+
00
